ash/Binop.py
ash/Subprog.py
ash/Translator.py
ash/Unop.py
ash/__init__.py
ash/ash.py
ash_assembly-0.0.2.dist-info/LICENSE
ash_assembly-0.0.2.dist-info/METADATA
ash_assembly-0.0.2.dist-info/WHEEL
ash_assembly-0.0.2.dist-info/top_level.txt
ash_assembly-0.0.2.dist-info/RECORD
