Metadata-Version: 2.1
Name: ash-assembly
Version: 0.0.2
Summary: ASH Assembly Shorthand Syntax
Home-page: https://github.com/herbstwetter/ash
Author: Alp
Author-email: alp@sneve.app
License: UNKNOWN
Platform: UNKNOWN
Classifier: Programming Language :: Python :: 3
Classifier: License :: OSI Approved :: MIT License
Classifier: Operating System :: OS Independent
Requires-Python: >=3.6
License-File: LICENSE
